{
  "app": "Fractal Wavetable START-END Morph Export",
  "app_file": "fractal_wt_start_end_morph_tabs_v6.py",
  "bulk_generation": {
    "directions": [
      "START_TO_END",
      "END_TO_START"
    ],
    "enabled": true,
    "epoch": 1781197276,
    "requested_iterations": 100,
    "serial_number": 10
  },
  "created_epoch": 1781197303,
  "created_local_time": "2026-06-12 05:01:43 +1200",
  "direction": "START_TO_END",
  "end_patch": {
    "am": 90,
    "core_seed": 2310,
    "fm": 2,
    "fm_range": {
      "cents": 1200.0,
      "label": "\u00b11200 cents (1 octave)",
      "octaves": 1.0
    },
    "fm_range_cents": 1200.0,
    "fm_range_label": "\u00b11200 cents (1 octave)",
    "growth_3_step": 1417,
    "growth_9_step": 2357,
    "legacy_internal": {
      "after_end": 3724,
      "after_start": 2932,
      "before_end": 42,
      "before_start": 321,
      "fm_range_label": "\u00b11200 cents (1 octave)",
      "pot1": 2310,
      "pot2": 1417,
      "pot3": 2357
    },
    "pwm": 198,
    "result_end": 42,
    "result_start": 321,
    "source_end": 3724,
    "source_start": 2932,
    "wavetable_type": 12,
    "wavetable_type_info": {
      "description": "Takes the lower of the two sources at each sample",
      "id": 12,
      "name": "Min",
      "option_label": "12 - Min - Takes the lower of the two sources at each sample"
    },
    "window_scale": {
      "max": 4096,
      "min": 0
    }
  },
  "files": {
    "filename_prefix": "fractal_wt_morph_bulk_2s",
    "json": "fractal_wt_morph_bulk_2s_1781197276_0010_START_TO_END.json",
    "json_path": "/tmp/fractal/2-seconds/fractal_wt_morph_bulk_2s_1781197276_0010_START_TO_END.json",
    "wav": "fractal_wt_morph_bulk_2s_1781197276_0010_START_TO_END.wav",
    "wav_path": "/tmp/fractal/2-seconds/fractal_wt_morph_bulk_2s_1781197276_0010_START_TO_END.wav"
  },
  "output_processing": {
    "bit_depth": "16-bit PCM",
    "bit_depth_info": {
      "bits": 16,
      "label": "16-bit PCM",
      "sample_format": "pcm_s16",
      "wav_container_bits": 16
    },
    "dc_removal": "Per cycle",
    "headroom_db": -0.1,
    "normalise": "Per cycle peak",
    "sample_rate": 44100
  },
  "patches": {
    "end_effective": {
      "am": 90,
      "core_seed": 2310,
      "fm": 2,
      "fm_range": {
        "cents": 1200.0,
        "label": "\u00b11200 cents (1 octave)",
        "octaves": 1.0
      },
      "fm_range_cents": 1200.0,
      "fm_range_label": "\u00b11200 cents (1 octave)",
      "growth_3_step": 1417,
      "growth_9_step": 2357,
      "legacy_internal": {
        "after_end": 3724,
        "after_start": 2932,
        "before_end": 42,
        "before_start": 321,
        "fm_range_label": "\u00b11200 cents (1 octave)",
        "pot1": 2310,
        "pot2": 1417,
        "pot3": 2357
      },
      "pwm": 198,
      "result_end": 42,
      "result_start": 321,
      "source_end": 3724,
      "source_start": 2932,
      "wavetable_type": 12,
      "wavetable_type_info": {
        "description": "Takes the lower of the two sources at each sample",
        "id": 12,
        "name": "Min",
        "option_label": "12 - Min - Takes the lower of the two sources at each sample"
      },
      "window_scale": {
        "max": 4096,
        "min": 0
      }
    },
    "end_raw": {
      "am": 90,
      "core_seed": 2310,
      "fm": 2,
      "fm_range": {
        "cents": 1200.0,
        "label": "\u00b11200 cents (1 octave)",
        "octaves": 1.0
      },
      "fm_range_cents": 1200.0,
      "fm_range_label": "\u00b11200 cents (1 octave)",
      "growth_3_step": 1417,
      "growth_9_step": 2357,
      "legacy_internal": {
        "after_end": 3724,
        "after_start": 2932,
        "before_end": 42,
        "before_start": 321,
        "fm_range_label": "\u00b11200 cents (1 octave)",
        "pot1": 2310,
        "pot2": 1417,
        "pot3": 2357
      },
      "pwm": 198,
      "result_end": 42,
      "result_start": 321,
      "source_end": 3724,
      "source_start": 2932,
      "wavetable_type": 8,
      "wavetable_type_info": {
        "description": "8-bit source collision using bitwise OR",
        "id": 8,
        "name": "Bit OR",
        "option_label": "8 - Bit OR - 8-bit source collision using bitwise OR"
      },
      "window_scale": {
        "max": 4096,
        "min": 0
      }
    },
    "start_effective": {
      "am": 180,
      "core_seed": 3850,
      "fm": 182,
      "fm_range": {
        "cents": 1200.0,
        "label": "\u00b11200 cents (1 octave)",
        "octaves": 1.0
      },
      "fm_range_cents": 1200.0,
      "fm_range_label": "\u00b11200 cents (1 octave)",
      "growth_3_step": 1024,
      "growth_9_step": 3942,
      "legacy_internal": {
        "after_end": 1641,
        "after_start": 1810,
        "before_end": 4030,
        "before_start": 1691,
        "fm_range_label": "\u00b11200 cents (1 octave)",
        "pot1": 3850,
        "pot2": 1024,
        "pot3": 3942
      },
      "pwm": 178,
      "result_end": 4030,
      "result_start": 1691,
      "source_end": 1641,
      "source_start": 1810,
      "wavetable_type": 12,
      "wavetable_type_info": {
        "description": "Takes the lower of the two sources at each sample",
        "id": 12,
        "name": "Min",
        "option_label": "12 - Min - Takes the lower of the two sources at each sample"
      },
      "window_scale": {
        "max": 4096,
        "min": 0
      }
    },
    "start_raw": {
      "am": 180,
      "core_seed": 3850,
      "fm": 182,
      "fm_range": {
        "cents": 1200.0,
        "label": "\u00b11200 cents (1 octave)",
        "octaves": 1.0
      },
      "fm_range_cents": 1200.0,
      "fm_range_label": "\u00b11200 cents (1 octave)",
      "growth_3_step": 1024,
      "growth_9_step": 3942,
      "legacy_internal": {
        "after_end": 1641,
        "after_start": 1810,
        "before_end": 4030,
        "before_start": 1691,
        "fm_range_label": "\u00b11200 cents (1 octave)",
        "pot1": 3850,
        "pot2": 1024,
        "pot3": 3942
      },
      "pwm": 178,
      "result_end": 4030,
      "result_start": 1691,
      "source_end": 1641,
      "source_start": 1810,
      "wavetable_type": 24,
      "wavetable_type_info": {
        "description": "Low-pass smoothed source average",
        "id": 24,
        "name": "Smooth Average",
        "option_label": "24 - Smooth Average - Low-pass smoothed source average"
      },
      "window_scale": {
        "max": 4096,
        "min": 0
      }
    }
  },
  "render_notes": [
    "after start>end; wrapped/clamped 1810\u21921641",
    "after start>end; wrapped/clamped 1815\u21921651",
    "after start>end; wrapped/clamped 1820\u21921660",
    "after start>end; wrapped/clamped 1825\u21921670",
    "after start>end; wrapped/clamped 1830\u21921679",
    "after start>end; wrapped/clamped 1836\u21921689",
    "after start>end; wrapped/clamped 1841\u21921698",
    "after start>end; wrapped/clamped 1846\u21921708",
    "after start>end; wrapped/clamped 1851\u21921717",
    "after start>end; wrapped/clamped 1856\u21921727",
    "after start>end; wrapped/clamped 1861\u21921736",
    "after start>end; wrapped/clamped 1866\u21921746",
    "after start>end; wrapped/clamped 1871\u21921755",
    "after start>end; wrapped/clamped 1877\u21921765",
    "after start>end; wrapped/clamped 1882\u21921774",
    "after start>end; wrapped/clamped 1887\u21921784",
    "after start>end; wrapped/clamped 1892\u21921793",
    "after start>end; wrapped/clamped 1897\u21921803",
    "after start>end; wrapped/clamped 1902\u21921812",
    "after start>end; wrapped/clamped 1907\u21921822"
  ],
  "reverse": false,
  "schema": {
    "compatibility": {
      "introduced_in": "fractal_wt_start_end_morph_tabs_v6.py",
      "legacy_internal_fields_preserved": true
    },
    "curve_amount": {
      "high_values": "Fast start, slower finish.",
      "linear": 127,
      "low_values": "Slow start, faster finish.",
      "range": [
        1,
        255
      ]
    },
    "description": "Sidecar metadata for a Fractal Wavetable START/END morph WAV export.",
    "direction_codes": {
      "END_TO_START": "Render morph position from END to START.",
      "START_TO_END": "Render morph position from START to END."
    },
    "name": "fractal_wavetable_morph_sidecar",
    "patch_field_notes": {
      "core_seed": "User-facing 12-bit Core Seed control, internally pot1.",
      "fm_range.cents": "Machine-readable FM pitch range in cents.",
      "growth_3_step": "User-facing 3-Step Growth control, internally pot2.",
      "growth_9_step": "User-facing 9-Step Growth control, internally pot3.",
      "legacy_internal": "Original internal field names retained to make future importers backwards-compatible with the generator code.",
      "result_start/result_end": "User-facing Result Window values on the 0..4096 window scale. Export v6 maps these from the internal before_start/before_end fields, per current JSON naming convention.",
      "source_start/source_end": "User-facing Source Window values on the 0..4096 window scale. Export v6 maps these from the internal after_start/after_end fields, per current JSON naming convention.",
      "wavetable_type": "Integer wavetable mode ID."
    },
    "version": 3
  },
  "schema_version": 3,
  "shared_settings": {
    "fm_pitch_range_is_shared": true,
    "frequency_hz": 110.0,
    "shared_fm_pitch_range": {
      "cents": 1200.0,
      "label": "\u00b11200 cents (1 octave)",
      "octaves": 1.0
    },
    "shared_fm_range": {
      "cents": 1200.0,
      "label": "\u00b11200 cents (1 octave)",
      "octaves": 1.0
    },
    "shared_wavetable_type": {
      "description": "First half 3-step source, second half 9-step source",
      "id": 3,
      "name": "3\u21929 Splice",
      "option_label": "3 - 3\u21929 Splice - First half 3-step source, second half 9-step source"
    },
    "volume": 0.2,
    "wavetable_type_is_shared": true
  },
  "start_patch": {
    "am": 180,
    "core_seed": 3850,
    "fm": 182,
    "fm_range": {
      "cents": 1200.0,
      "label": "\u00b11200 cents (1 octave)",
      "octaves": 1.0
    },
    "fm_range_cents": 1200.0,
    "fm_range_label": "\u00b11200 cents (1 octave)",
    "growth_3_step": 1024,
    "growth_9_step": 3942,
    "legacy_internal": {
      "after_end": 1641,
      "after_start": 1810,
      "before_end": 4030,
      "before_start": 1691,
      "fm_range_label": "\u00b11200 cents (1 octave)",
      "pot1": 3850,
      "pot2": 1024,
      "pot3": 3942
    },
    "pwm": 178,
    "result_end": 4030,
    "result_start": 1691,
    "source_end": 1641,
    "source_start": 1810,
    "wavetable_type": 12,
    "wavetable_type_info": {
      "description": "Takes the lower of the two sources at each sample",
      "id": 12,
      "name": "Min",
      "option_label": "12 - Min - Takes the lower of the two sources at each sample"
    },
    "window_scale": {
      "max": 4096,
      "min": 0
    }
  },
  "summary": {
    "bit_depth": "16-bit PCM",
    "bit_depth_info": {
      "bits": 16,
      "label": "16-bit PCM",
      "sample_format": "pcm_s16",
      "wav_container_bits": 16
    },
    "duration_mode_code": "seconds",
    "duration_seconds": 2.0,
    "frequency": 110.0,
    "nominal_cycles": 220.0,
    "requested_mode": "Seconds",
    "requested_value": 2.0,
    "sample_count": 88200,
    "sample_rate": 44100,
    "samples_per_cycle": 400.90909090909093,
    "suggestions": [
      "172.266 Hz gives exactly 256 samples/cycle at 44100 Hz",
      "86.1328 Hz gives exactly 512 samples/cycle at 44100 Hz",
      "43.0664 Hz gives exactly 1024 samples/cycle at 44100 Hz"
    ],
    "warnings": []
  },
  "transition": {
    "curve_amount": 127,
    "curve_amount_linear": 127,
    "curve_amount_range": [
      1,
      255
    ],
    "curve_mode": "Bend",
    "cycle_stepped": true,
    "different_fm_pitch_ranges": false,
    "different_wavetable_types": false,
    "wavetable_type_transition": "shared_type"
  }
}